Workbook

Sheet Instructions
A1: Rez Weekly Report — Instructions
A3: IMPORTANT: Column headers in each import tab are PLACEHOLDERS. After your first CSV export from each platform, update the header row in each import tab to match your actual column names. The formulas use MATCH() on these headers — they must match exactly.
A5: LABOR COST NOTE: The 'Est. Labor Cost (manual)' cell in each Location Calc tab requires manual entry for v1. Enter the total labor cost for that location from your Square Labor report each week. Labor Cost % is then computed automatically. Phase 2 will automate this via Square Labor CSV import.
A7: WEEKLY CADENCE
A8: Every Monday morning: clear last week's data from each import tab (delete rows 3 and below — keep rows 1 and 2), paste new CSVs, then check the Summary tab.
A10: HOW TO EXPORT & PASTE — SQUARE
A11: 1. Log into Square Dashboard
A12: 2. Go to: Reports > Sales Summary
A13: 3. Select date range: Mon–Sun of the week you are reporting
A14: 4. Click 'Export CSV'
A15: 5. Open the CSV, select all, copy
A16: 6. Click into cell A3 of the Square-Import tab in this workbook
... A68: NOTE: Square Labor column headers in the Labor-Import tab are PLACEHOLDERS — update Labor-Import row 2 headers to match Rez's actual Square Labor export column names before using Overtime-Tracker formulas in production.

Sheet Square-Import
A1: PLACEHOLDER HEADERS — Update row 2 to match your actual CSV export column names exactly.
A2: Date | B2: Location | C2: Category | D2: Net Sales | E2: Gross Sales | F2: Discounts | G2: Tax | H2: Tips | I2: Refunds
A3: [Date — text/date] | B3: [Location — text/date] | C3: [Category — text/date] | D3: =IF(ISNUMBER(INDEX(Square-Import!A:Z,4,MATCH("Net Sales",Square-Import!2:2,0))),"OK","PASTE ERROR - Net Sales is not a number") | E3: =IF(ISNUMBER(INDEX(Square-Import!A:Z,4,MATCH("Gross Sales",Square-Import!2:2,0))),"OK","PASTE ERROR - Gross Sales is not a number") | F3: [Discounts — text/date] | G3: [Tax — text/date] | H3: [Tips — text/date] | I3: [Refunds — text/date]
A4: 2026-03-09 | B4: Moto Medi Lubbock | C4: Food & Drink | D4: 1840 | E4: 1950 | F4: 55 | G4: 152.1 | H4: 0 | I4: 15
A5: 2026-03-10 | B5: Moto Medi Lubbock | C5: Food & Drink | D5: 2120.5 | E5: 2230 | F5: 42 | G5: 175.32 | H5: 0 | I5: 12.5
A6: 2026-03-11 | B6: Moto Medi Lubbock | C6: Food & Drink | D6: 2340 | E6: 2450 | F6: 60 | G6: 193.62 | H6: 0 | I6: 50
A7: 2026-03-12 | B7: Moto Medi Lubbock | C7: Food & Drink | D7: 2050.75 | E7: 2160 | F7: 55.25 | G7: 169.7 | H7: 0 | I7: 29.25
A8: 2026-03-13 | B8: Moto Medi Lubbock | C8: Food & Drink | D8: 2490 | E8: 2610 | F8: 70 | G8: 205.93 | H8: 0 | I8: 30
A9: 2026-03-09 | B9: Moto Medi Amarillo | C9: Food & Drink | D9: 1540 | E9: 1640 | F9: 45 | G9: 127.41 | H9: 0 | I9: 10
A10: 2026-03-10 | B10: Moto Medi Amarillo | C10: Food & Drink | D10: 1680.25 | E10: 1790 | F10: 60 | G10: 139.04 | H10: 0 | I10: 29.75
A11: 2026-03-11 | B11: Moto Medi Amarillo | C11: Food & Drink | D11: 1820 | E11: 1940 | F11: 65 | G11: 150.56 | H11: 0 | I11: 20
A12: 2026-03-12 | B12: Moto Medi Amarillo | C12: Food & Drink | D12: 1590.5 | E12: 1690 | F12: 50 | G12: 131.54 | H12: 0 | I12: 19.5
A13: 2026-03-13 | B13: Moto Medi Amarillo | C13: Food & Drink | D13: 1920 | E13: 2040 | F13: 70 | G13: 158.88 | H13: 0 | I13: 20
A14: 2026-03-09 | B14: Moto Medi 3rd | C14: Food & Drink | D14: 1240 | E14: 1320 | F14: 35 | G14: 102.59 | H14: 0 | I14: 10
A15: 2026-03-10 | B15: Moto Medi 3rd | C15: Food & Drink | D15: 1380.5 | E15: 1470 | F15: 40 | G15: 114.16 | H15: 0 | I15: 19.5
... A28: 2026-03-13 | B28: Tikka Shack 2 | C28: Food & Drink | D28: 1140 | E28: 1220 | F28: 33 | G28: 94.25 | H28: 0 | I28: 13
A30: Last Updated:

Sheet DoorDash-Import
A1: PLACEHOLDER HEADERS — Update row 2 to match your actual CSV export column names exactly.
A2: Date | B2: Store Name | C2: Subtotal | D2: Commission | E2: Net Payout | F2: Order Count | G2: Avg Order Value
A3: [Date — text/date] | B3: [Store Name — text/date] | C3: [Subtotal — text/date] | D3: [Commission — text/date] | E3: =IF(ISNUMBER(INDEX(DoorDash-Import!A:Z,4,MATCH("Net Payout",DoorDash-Import!2:2,0))),"OK","PASTE ERROR - Net Payout is not a number") | F3: =IF(ISNUMBER(INDEX(DoorDash-Import!A:Z,4,MATCH("Order Count",DoorDash-Import!2:2,0))),"OK","PASTE ERROR - Order Count is not a number") | G3: [Avg Order Value — text/date]
A4: 2026-03-09 | B4: Moto Medi Lubbock | C4: 980 | D4: 196 | E4: 784 | F4: 52 | G4: 18.85
A5: 2026-03-10 | B5: Moto Medi Lubbock | C5: 1100 | D5: 220 | E5: 880 | F5: 58 | G5: 18.97
A6: 2026-03-11 | B6: Moto Medi Lubbock | C6: 1240 | D6: 248 | E6: 992 | F6: 64 | G6: 19.38
A7: 2026-03-12 | B7: Moto Medi Lubbock | C7: 1050 | D7: 210 | E7: 840 | F7: 55 | G7: 19.09
A8: 2026-03-13 | B8: Moto Medi Lubbock | C8: 1320 | D8: 264 | E8: 1056 | F8: 70 | G8: 18.86
A9: 2026-03-09 | B9: Moto Medi Amarillo | C9: 720 | D9: 144 | E9: 576 | F9: 40 | G9: 18
A10: 2026-03-10 | B10: Moto Medi Amarillo | C10: 810 | D10: 162 | E10: 648 | F10: 44 | G10: 18.41
A11: 2026-03-11 | B11: Moto Medi Amarillo | C11: 890 | D11: 178 | E11: 712 | F11: 48 | G11: 18.54
A12: 2026-03-12 | B12: Moto Medi Amarillo | C12: 760 | D12: 152 | E12: 608 | F12: 42 | G12: 18.1
A13: 2026-03-13 | B13: Moto Medi Amarillo | C13: 940 | D13: 188 | E13: 752 | F13: 52 | G13: 18.08
A14: 2026-03-09 | B14: Moto Medi 3rd | C14: 560 | D14: 112 | E14: 448 | F14: 32 | G14: 17.5
A15: 2026-03-10 | B15: Moto Medi 3rd | C15: 620 | D15: 124 | E15: 496 | F15: 35 | G15: 17.71
... A28: 2026-03-13 | B28: Tikka Shack 2 | C28: 570 | D28: 114 | E28: 456 | F28: 33 | G28: 17.27
A30: Last Updated:

Sheet UberEats-Import
A1: PLACEHOLDER HEADERS — Update row 2 to match your actual CSV export column names exactly.
A2: Date | B2: Restaurant Name | C2: Sales | D2: Marketplace Fee | E2: Net Payout | F2: Trips | G2: Avg Basket
A3: [Date — text/date] | B3: [Restaurant Name — text/date] | C3: =IF(ISNUMBER(INDEX(UberEats-Import!A:Z,4,MATCH("Sales",UberEats-Import!2:2,0))),"OK","PASTE ERROR - Sales is not a number") | D3: [Marketplace Fee — text/date] | E3: =IF(ISNUMBER(INDEX(UberEats-Import!A:Z,4,MATCH("Net Payout",UberEats-Import!2:2,0))),"OK","PASTE ERROR - Net Payout is not a number") | F3: =IF(ISNUMBER(INDEX(UberEats-Import!A:Z,4,MATCH("Trips",UberEats-Import!2:2,0))),"OK","PASTE ERROR - Trips is not a number") | G3: [Avg Basket — text/date]
A4: 2026-03-09 | B4: Moto Medi Lubbock | C4: 740 | D4: 185 | E4: 555 | F4: 40 | G4: 18.5
A5: 2026-03-10 | B5: Moto Medi Lubbock | C5: 820 | D5: 205 | E5: 615 | F5: 44 | G5: 18.64
A6: 2026-03-11 | B6: Moto Medi Lubbock | C6: 940 | D6: 235 | E6: 705 | F6: 50 | G6: 18.8
A7: 2026-03-12 | B7: Moto Medi Lubbock | C7: 780 | D7: 195 | E7: 585 | F7: 42 | G7: 18.57
A8: 2026-03-13 | B8: Moto Medi Lubbock | C8: 980 | D8: 245 | E8: 735 | F8: 53 | G8: 18.49
A9: 2026-03-09 | B9: Moto Medi Amarillo | C9: 560 | D9: 140 | E9: 420 | F9: 30 | G9: 18.67
A10: 2026-03-10 | B10: Moto Medi Amarillo | C10: 610 | D10: 152.5 | E10: 457.5 | F10: 33 | G10: 18.48
A11: 2026-03-11 | B11: Moto Medi Amarillo | C11: 680 | D11: 170 | E11: 510 | F11: 37 | G11: 18.38
A12: 2026-03-12 | B12: Moto Medi Amarillo | C12: 590 | D12: 147.5 | E12: 442.5 | F12: 32 | G12: 18.44
A13: 2026-03-13 | B13: Moto Medi Amarillo | C13: 720 | D13: 180 | E13: 540 | F13: 39 | G13: 18.46
A14: 2026-03-09 | B14: Moto Medi 3rd | C14: 420 | D14: 105 | E14: 315 | F14: 23 | G14: 18.26
A15: 2026-03-10 | B15: Moto Medi 3rd | C15: 470 | D15: 117.5 | E15: 352.5 | F15: 25 | G15: 18.8
... A28: 2026-03-13 | B28: Tikka Shack 2 | C28: 420 | D28: 105 | E28: 315 | F28: 24 | G28: 17.5
A30: Last Updated:

Sheet Grubhub-Import
A1: PLACEHOLDER HEADERS — Update row 2 to match your actual CSV export column names exactly.
A2: Date | B2: Restaurant | C2: Food Sales | D2: Delivery Fee | E2: Grubhub Commission | F2: Net Payout | G2: Orders
A3: [Date — text/date] | B3: [Restaurant — text/date] | C3: =IF(ISNUMBER(INDEX(Grubhub-Import!A:Z,4,MATCH("Food Sales",Grubhub-Import!2:2,0))),"OK","PASTE ERROR - Food Sales is not a number") | D3: [Delivery Fee — text/date] | E3: [Grubhub Commission — text/date] | F3: =IF(ISNUMBER(INDEX(Grubhub-Import!A:Z,4,MATCH("Net Payout",Grubhub-Import!2:2,0))),"OK","PASTE ERROR - Net Payout is not a number") | G3: =IF(ISNUMBER(INDEX(Grubhub-Import!A:Z,4,MATCH("Orders",Grubhub-Import!2:2,0))),"OK","PASTE ERROR - Orders is not a number")
A4: 2026-03-09 | B4: Moto Medi Lubbock | C4: 380 | D4: 45 | E4: 76 | F4: 259 | G4: 21
A5: 2026-03-10 | B5: Moto Medi Lubbock | C5: 420 | D5: 50 | E5: 84 | F5: 286 | G5: 23
A6: 2026-03-11 | B6: Moto Medi Lubbock | C6: 500 | D6: 58 | E6: 100 | F6: 342 | G6: 27
A7: 2026-03-12 | B7: Moto Medi Lubbock | C7: 410 | D7: 48 | E7: 82 | F7: 280 | G7: 22
A8: 2026-03-13 | B8: Moto Medi Lubbock | C8: 540 | D8: 62 | E8: 108 | F8: 370 | G8: 29
A9: 2026-03-09 | B9: Moto Medi Amarillo | C9: 280 | D9: 34 | E9: 56 | F9: 190 | G9: 16
A10: 2026-03-10 | B10: Moto Medi Amarillo | C10: 320 | D10: 38 | E10: 64 | F10: 218 | G10: 18
A11: 2026-03-11 | B11: Moto Medi Amarillo | C11: 370 | D11: 44 | E11: 74 | F11: 252 | G11: 20
A12: 2026-03-12 | B12: Moto Medi Amarillo | C12: 290 | D12: 35 | E12: 58 | F12: 197 | G12: 16
A13: 2026-03-13 | B13: Moto Medi Amarillo | C13: 400 | D13: 47 | E13: 80 | F13: 273 | G13: 22
A14: 2026-03-09 | B14: Moto Medi 3rd | C14: 200 | D14: 25 | E14: 40 | F14: 135 | G14: 11
A15: 2026-03-10 | B15: Moto Medi 3rd | C15: 230 | D15: 28 | E15: 46 | F15: 156 | G15: 13
... A28: 2026-03-13 | B28: Tikka Shack 2 | C28: 200 | D28: 24 | E28: 40 | F28: 136 | G28: 11
A30: Last Updated:

Sheet BEK-Import
A1: PLACEHOLDER HEADERS — Update row 2 to match your actual CSV export column names exactly.
A2: Invoice Date | B2: Invoice Number | C2: Item Description | D2: Category | E2: Quantity | F2: Unit Price | G2: Total
A3: [Invoice Date — text/date] | B3: [Invoice Number — text/date] | C3: [Item Description — text/date] | D3: [Category — text/date] | E3: =IF(ISNUMBER(INDEX(BEK-Import!A:Z,4,MATCH("Quantity",BEK-Import!2:2,0))),"OK","PASTE ERROR - Quantity is not a number") | F3: [Unit Price — text/date] | G3: =IF(ISNUMBER(INDEX(BEK-Import!A:Z,4,MATCH("Total",BEK-Import!2:2,0))),"OK","PASTE ERROR - Total is not a number")
A4: 2026-03-10 | B4: INV-2026-0901 | C4: Chicken Thighs 40lb Case | D4: Food | E4: 2 | F4: 89.5 | G4: 179
A5: 2026-03-10 | B5: INV-2026-0901 | C5: Jasmine Rice 50lb Bag | D5: Food | E5: 3 | F5: 42 | G5: 126
A6: 2026-03-10 | B6: INV-2026-0901 | C6: Canola Oil 35lb Jug | D6: Food | E6: 4 | F6: 38.75 | G6: 155
A7: 2026-03-10 | B7: INV-2026-0901 | C7: To-Go Containers 200ct | D7: Supplies | E7: 5 | F7: 18.5 | G7: 92.5
A8: 2026-03-10 | B8: INV-2026-0901 | C8: Napkins 4000ct | D8: Supplies | E8: 2 | F8: 22 | G8: 44
A9: 2026-03-10 | B9: INV-2026-0902 | C9: Ground Beef 80/20 40lb | D9: Food | E9: 3 | F9: 92 | G9: 276
A10: 2026-03-10 | B10: INV-2026-0902 | C10: Paneer 10lb | D10: Food | E10: 4 | F10: 28.5 | G10: 114
A11: 2026-03-10 | B11: INV-2026-0902 | C11: Spice Blend — Tikka Masala | D11: Food | E11: 6 | F11: 14 | G11: 84
A12: 2026-03-10 | B12: INV-2026-0902 | C12: Gloves Medium 100ct Box | D12: Supplies | E12: 8 | F12: 9.75 | G12: 78
A13: 2026-03-10 | B13: INV-2026-0902 | C13: Cleaning Supplies Bundle | D13: Supplies | E13: 3 | F13: 31 | G13: 93
A14: 2026-03-13 | B14: INV-2026-0944 | C14: Chicken Thighs 40lb Case | D14: Food | E14: 3 | F14: 89.5 | G14: 268.5
A15: 2026-03-13 | B15: INV-2026-0944 | C15: Flatbread Dough 12pk | D15: Food | E15: 6 | F15: 19 | G15: 114
... A18: 2026-03-13 | B18: INV-2026-0944 | C18: Kraft Paper Roll 300ft | D18: Supplies | E18: 2 | F18: 27.5 | G18: 55
A20: Last Updated:

Sheet Employee-Roster
A1: Employee Name | B1: Square Name | C1: Location | D1: Hourly Rate | E1: Hire Date | F1: Pay Tier | G1: Notes | H1: Next Milestone Date | I1: Milestone Type | J1: Days Until Milestone | K1: Milestone Status
A2: Marcus Johnson | B2: Marcus Johnson | C2: MML | D2: 16.5 | E2: 2024-06-01 | F2: Line Cook | G2: Lead cook — Lubbock | H2: 2026-04-01 | I2: 90-Day Review | J2: =IFERROR(H2-TODAY(),"") | K2: =IF(J2="","",IF(J2<=0,"OVERDUE",IF(J2<=30,"SOON","OK")))
A3: Ashley Torres | B3: Ashley Torres | C3: MML | D3: 14 | E3: 2024-09-15 | F3: Cashier | G3: Cross-trained on prep | J3: =IFERROR(H3-TODAY(),"") | K3: =IF(J3="","",IF(J3<=0,"OVERDUE",IF(J3<=30,"SOON","OK")))
A4: Destiny Williams | B4: Destiny Williams | C4: MMA | D4: 14.5 | E4: 2025-01-10 | F4: Cashier | H4: 2026-06-01 | I4: 6-Month Check-In | J4: =IFERROR(H4-TODAY(),"") | K4: =IF(J4="","",IF(J4<=0,"OVERDUE",IF(J4<=30,"SOON","OK")))
A5: Robert Kim | B5: Robert Kim | C5: MMA | D5: 15.75 | E5: 2024-08-20 | F5: Line Cook | H5: 2026-08-20 | I5: Annual Review | J5: =IFERROR(H5-TODAY(),"") | K5: =IF(J5="","",IF(J5<=0,"OVERDUE",IF(J5<=30,"SOON","OK")))
A6: Jake Hernandez | B6: Jake Hernandez | C6: MM3 | D6: 15 | E6: 2025-03-01 | F6: Line Cook | G6: Newer location | H6: 2026-03-10 | I6: Food Handler Cert | J6: =IFERROR(H6-TODAY(),"") | K6: =IF(J6="","",IF(J6<=0,"OVERDUE",IF(J6<=30,"SOON","OK")))
A7: Priya Patel | B7: Priya Patel | C7: TS1 | D7: 16 | E7: 2024-07-14 | F7: Line Cook | G7: Tikka Shack specialist | H7: 2026-07-14 | I7: Annual Review | J7: =IFERROR(H7-TODAY(),"") | K7: =IF(J7="","",IF(J7<=0,"OVERDUE",IF(J7<=30,"SOON","OK")))
A8: Carlos Rivera | B8: Carlos Rivera | C8: TS1 | D8: 13.5 | E8: 2025-02-01 | F8: Cashier | H8: 2026-05-01 | I8: 90-Day Pay Review | J8: =IFERROR(H8-TODAY(),"") | K8: =IF(J8="","",IF(J8<=0,"OVERDUE",IF(J8<=30,"SOON","OK")))
A9: Keisha Brown | B9: Keisha Brown | C9: TS2 | D9: 14.25 | E9: 2024-11-05 | F9: Line Cook | H9: 2026-11-05 | I9: Annual Review | J9: =IFERROR(H9-TODAY(),"") | K9: =IF(J9="","",IF(J9<=0,"OVERDUE",IF(J9<=30,"SOON","OK")))
A10: Devon Scott | B10: Devon Scott | C10: MML | D10: 12.5 | E10: 2025-10-20 | F10: Kitchen Help | G10: Part-time | J10: =IFERROR(H10-TODAY(),"") | K10: =IF(J10="","",IF(J10<=0,"OVERDUE",IF(J10<=30,"SOON","OK")))
A11: Jasmine Lee | B11: Jasmine Lee | C11: TS2 | D11: 13 | E11: 2025-11-01 | F11: Cashier | G11: Part-time | J11: =IFERROR(H11-TODAY(),"") | K11: =IF(J11="","",IF(J11<=0,"OVERDUE",IF(J11<=30,"SOON","OK")))
A13: NOTE: 'Square Name' must match the employee name exactly as it appears in Square's clock-in export. This is the VLOOKUP key for labor cost calculations. Nicknames, capitalization, and spacing must match. Milestone columns H-K: enter Next Milestone Date (col H) and Milestone Type (col I) manually; Days Until Milestone (col J) and Status (col K) update automatically via formula.

Sheet Prior-Week
A1: Week Ending | B1: MML Net Revenue | C1: MML Purchase Cost % | D1: MML Labor Cost % | E1: MML Orders | F1: MML Avg Ticket | G1: MMA Net Revenue | H1: MMA Purchase Cost % | I1: MMA Labor Cost % | J1: MMA Orders | K1: MMA Avg Ticket | L1: MM3 Net Revenue | M1: MM3 Purchase Cost % | N1: MM3 Labor Cost % | O1: MM3 Orders | P1: MM3 Avg Ticket | Q1: TS1 Net Revenue | R1: TS1 Purchase Cost % | S1: TS1 Labor Cost % | T1: TS1 Orders | U1: TS1 Avg Ticket | V1: TS2 Net Revenue | W1: TS2 Purchase Cost % | X1: TS2 Labor Cost % | Y1: TS2 Orders | Z1: TS2 Avg Ticket
A2: 2026-03-09 | B2: 12050 | C2: 0.284 | D2: 0.312 | E2: 387 | F2: 19.1 | G2: 9820 | H2: 0.301 | I2: 0.298 | J2: 321 | K2: 18.85 | L2: 7640 | M2: 0.318 | N2: 0.305 | O2: 258 | P2: 18.92 | Q2: 6510 | R2: 0.312 | S2: 0.321 | T2: 215 | U2: 18.65 | V2: 5890 | W2: 0.296 | X2: 0.334 | Y2: 182 | Z2: 18.88
A3: 2026-03-16

Sheet MML-Calc
A1: Moto Medi Lubbock
A2: Week Ending: | B2: ='Summary'!B2
B3: This Week | C3: Prior Week | D3: WoW Change | E3: WoW %
A4: Revenue Breakdown
A5: Square Net Sales | B5: =IFERROR(SUMIFS(INDEX('Square-Import'!A:Z,0,MATCH("Net Sales",'Square-Import'!1:1,0)),INDEX('Square-Import'!A:Z,0,MATCH("Location",'Square-Import'!1:1,0)),"Moto Medi Lubbock"),0) | C5: 0 | D5: =B5-C5 | E5: =IF(C5>0,(B5-C5)/C5,0)
A6: DoorDash Net Revenue | B6: =IFERROR(SUMIFS(INDEX('DoorDash-Import'!A:Z,0,MATCH("Net Payout",'DoorDash-Import'!1:1,0)),INDEX('DoorDash-Import'!A:Z,0,MATCH("Store Name",'DoorDash-Import'!1:1,0)),"Moto Medi Lubbock"),0) | C6: 0 | D6: =B6-C6 | E6: =IF(C6>0,(B6-C6)/C6,0)
A7: UberEats Net Revenue | B7: =IFERROR(SUMIFS(INDEX('UberEats-Import'!A:Z,0,MATCH("Net Payout",'UberEats-Import'!1:1,0)),INDEX('UberEats-Import'!A:Z,0,MATCH("Restaurant Name",'UberEats-Import'!1:1,0)),"Moto Medi Lubbock"),0) | C7: 0 | D7: =B7-C7 | E7: =IF(C7>0,(B7-C7)/C7,0)
A8: Grubhub Net Revenue | B8: =IFERROR(SUMIFS(INDEX('Grubhub-Import'!A:Z,0,MATCH("Net Payout",'Grubhub-Import'!1:1,0)),INDEX('Grubhub-Import'!A:Z,0,MATCH("Restaurant",'Grubhub-Import'!1:1,0)),"Moto Medi Lubbock"),0) | C8: 0 | D8: =B8-C8 | E8: =IF(C8>0,(B8-C8)/C8,0)
A9: Total Net Revenue | B9: =SUM(B5:B8) | C9: =IFERROR(INDEX('Prior-Week'!A:Z,MATCH(B2-7,'Prior-Week'!A:A,0),2),0) | D9: =B9-C9 | E9: =IF(C9>0,(B9-C9)/C9,0)
A10: Cost Metrics
A12: BEK Purchases | B12: =IFERROR(SUMIF(INDEX('BEK-Import'!A:Z,0,MATCH("Category",'BEK-Import'!1:1,0)),"Food",INDEX('BEK-Import'!A:Z,0,MATCH("Total",'BEK-Import'!1:1,0)))/5,IFERROR(SUMIF(INDEX('BEK-Import'!A:Z,0,MATCH("Total",'BEK-Import'!1:1,0)),">0",INDEX('BEK-Import'!A:Z,0,MATCH("Total",'BEK-Import'!1:1,0)))/5,0))
A13: Purchase Cost % | B13: =IF(B9>0,B12/B9,0) | C13: =IFERROR(INDEX('Prior-Week'!A:Z,MATCH(B2-7,'Prior-Week'!A:A,0),3),0) | D13: =B13-C13 | E13: =IF(C13>0,(B13-C13)/C13,0)
A14: Labor
A16: Est. Labor Cost (manual) | B16: 0
A17: Labor Cost % | B17: =IF(B9>0,B16/B9,0) | C17: =IFERROR(INDEX('Prior-Week'!A:Z,MATCH(B2-7,'Prior-Week'!A:A,0),4),0) | D17: =B17-C17 | E17: =IF(C17>0,(B17-C17)/C17,0)
A18: Volume
A20: Total Orders | B20: =IFERROR(SUMIFS(INDEX('Square-Import'!A:Z,0,MATCH("Order Count",'Square-Import'!1:1,0)),INDEX('Square-Import'!A:Z,0,MATCH("Location",'Square-Import'!1:1,0)),"Moto Medi Lubbock"),0)+IFERROR(SUMIFS(INDEX('DoorDash-Import'!A:Z,0,MATCH("Order Count",'DoorDash-Import'!1:1,0)),INDEX('DoorDash-Import'!A:Z,0,MATCH("Store Name",'DoorDash-Import'!1:1,0)),"Moto Medi Lubbock"),0)+IFERROR(SUMIFS(INDEX('UberEats-Import'!A:Z,0,MATCH("Trips",'UberEats-Import'!1:1,0)),INDEX('UberEats-Import'!A:Z,0,MATCH("Restaurant Name",'UberEats-Import'!1:1,0)),"Moto Medi Lubbock"),0)+IFERROR(SUMIFS(INDEX('Grubhub-Import'!A:Z,0,MATCH("Orders",'Grubhub-Import'!1:1,0)),INDEX('Grubhub-Import'!A:Z,0,MATCH("Restaurant",'Grubhub-Import'!1:1,0)),"Moto Medi Lubbock"),0) | C20: =IFERROR(INDEX('Prior-Week'!A:Z,MATCH(B2-7,'Prior-Week'!A:A,0),5),0) | D20: =B20-C20 | E20: =IF(C20>0,(B20-C20)/C20,0)
A21: Avg Ticket Size | B21: =IF(B20>0,B9/B20,0) | C21: =IFERROR(INDEX('Prior-Week'!A:Z,MATCH(B2-7,'Prior-Week'!A:A,0),6),0) | D21: =B21-C21 | E21: =IF(C21>0,(B21-C21)/C21,0)
A23: [MML] Labor Cost requires manual entry — enter weekly labor total in the yellow B16 cell. Phase 2 automates via Square Labor CSV import (PAY-01).

Sheet MMA-Calc
A1: Moto Medi Amarillo
A2: Week Ending: | B2: ='Summary'!B2
B3: This Week | C3: Prior Week | D3: WoW Change | E3: WoW %
A4: Revenue Breakdown
A5: Square Net Sales | B5: =IFERROR(SUMIFS(INDEX('Square-Import'!A:Z,0,MATCH("Net Sales",'Square-Import'!1:1,0)),INDEX('Square-Import'!A:Z,0,MATCH("Location",'Square-Import'!1:1,0)),"Moto Medi Amarillo"),0) | C5: 0 | D5: =B5-C5 | E5: =IF(C5>0,(B5-C5)/C5,0)
A6: DoorDash Net Revenue | B6: =IFERROR(SUMIFS(INDEX('DoorDash-Import'!A:Z,0,MATCH("Net Payout",'DoorDash-Import'!1:1,0)),INDEX('DoorDash-Import'!A:Z,0,MATCH("Store Name",'DoorDash-Import'!1:1,0)),"Moto Medi Amarillo"),0) | C6: 0 | D6: =B6-C6 | E6: =IF(C6>0,(B6-C6)/C6,0)
A7: UberEats Net Revenue | B7: =IFERROR(SUMIFS(INDEX('UberEats-Import'!A:Z,0,MATCH("Net Payout",'UberEats-Import'!1:1,0)),INDEX('UberEats-Import'!A:Z,0,MATCH("Restaurant Name",'UberEats-Import'!1:1,0)),"Moto Medi Amarillo"),0) | C7: 0 | D7: =B7-C7 | E7: =IF(C7>0,(B7-C7)/C7,0)
A8: Grubhub Net Revenue | B8: =IFERROR(SUMIFS(INDEX('Grubhub-Import'!A:Z,0,MATCH("Net Payout",'Grubhub-Import'!1:1,0)),INDEX('Grubhub-Import'!A:Z,0,MATCH("Restaurant",'Grubhub-Import'!1:1,0)),"Moto Medi Amarillo"),0) | C8: 0 | D8: =B8-C8 | E8: =IF(C8>0,(B8-C8)/C8,0)
A9: Total Net Revenue | B9: =SUM(B5:B8) | C9: =IFERROR(INDEX('Prior-Week'!A:Z,MATCH(B2-7,'Prior-Week'!A:A,0),7),0) | D9: =B9-C9 | E9: =IF(C9>0,(B9-C9)/C9,0)
A10: Cost Metrics
A12: BEK Purchases | B12: =IFERROR(SUMIF(INDEX('BEK-Import'!A:Z,0,MATCH("Category",'BEK-Import'!1:1,0)),"Food",INDEX('BEK-Import'!A:Z,0,MATCH("Total",'BEK-Import'!1:1,0)))/5,IFERROR(SUMIF(INDEX('BEK-Import'!A:Z,0,MATCH("Total",'BEK-Import'!1:1,0)),">0",INDEX('BEK-Import'!A:Z,0,MATCH("Total",'BEK-Import'!1:1,0)))/5,0))
A13: Purchase Cost % | B13: =IF(B9>0,B12/B9,0) | C13: =IFERROR(INDEX('Prior-Week'!A:Z,MATCH(B2-7,'Prior-Week'!A:A,0),8),0) | D13: =B13-C13 | E13: =IF(C13>0,(B13-C13)/C13,0)
A14: Labor
A16: Est. Labor Cost (manual) | B16: 0
A17: Labor Cost % | B17: =IF(B9>0,B16/B9,0) | C17: =IFERROR(INDEX('Prior-Week'!A:Z,MATCH(B2-7,'Prior-Week'!A:A,0),9),0) | D17: =B17-C17 | E17: =IF(C17>0,(B17-C17)/C17,0)
A18: Volume
A20: Total Orders | B20: =IFERROR(SUMIFS(INDEX('Square-Import'!A:Z,0,MATCH("Order Count",'Square-Import'!1:1,0)),INDEX('Square-Import'!A:Z,0,MATCH("Location",'Square-Import'!1:1,0)),"Moto Medi Amarillo"),0)+IFERROR(SUMIFS(INDEX('DoorDash-Import'!A:Z,0,MATCH("Order Count",'DoorDash-Import'!1:1,0)),INDEX('DoorDash-Import'!A:Z,0,MATCH("Store Name",'DoorDash-Import'!1:1,0)),"Moto Medi Amarillo"),0)+IFERROR(SUMIFS(INDEX('UberEats-Import'!A:Z,0,MATCH("Trips",'UberEats-Import'!1:1,0)),INDEX('UberEats-Import'!A:Z,0,MATCH("Restaurant Name",'UberEats-Import'!1:1,0)),"Moto Medi Amarillo"),0)+IFERROR(SUMIFS(INDEX('Grubhub-Import'!A:Z,0,MATCH("Orders",'Grubhub-Import'!1:1,0)),INDEX('Grubhub-Import'!A:Z,0,MATCH("Restaurant",'Grubhub-Import'!1:1,0)),"Moto Medi Amarillo"),0) | C20: =IFERROR(INDEX('Prior-Week'!A:Z,MATCH(B2-7,'Prior-Week'!A:A,0),10),0) | D20: =B20-C20 | E20: =IF(C20>0,(B20-C20)/C20,0)
A21: Avg Ticket Size | B21: =IF(B20>0,B9/B20,0) | C21: =IFERROR(INDEX('Prior-Week'!A:Z,MATCH(B2-7,'Prior-Week'!A:A,0),11),0) | D21: =B21-C21 | E21: =IF(C21>0,(B21-C21)/C21,0)
A23: [MMA] Labor Cost requires manual entry — enter weekly labor total in the yellow B16 cell. Phase 2 automates via Square Labor CSV import (PAY-01).

Sheet MM3-Calc
A1: Moto Medi 3rd
A2: Week Ending: | B2: ='Summary'!B2
B3: This Week | C3: Prior Week | D3: WoW Change | E3: WoW %
A4: Revenue Breakdown
A5: Square Net Sales | B5: =IFERROR(SUMIFS(INDEX('Square-Import'!A:Z,0,MATCH("Net Sales",'Square-Import'!1:1,0)),INDEX('Square-Import'!A:Z,0,MATCH("Location",'Square-Import'!1:1,0)),"Moto Medi 3rd"),0) | C5: 0 | D5: =B5-C5 | E5: =IF(C5>0,(B5-C5)/C5,0)
A6: DoorDash Net Revenue | B6: =IFERROR(SUMIFS(INDEX('DoorDash-Import'!A:Z,0,MATCH("Net Payout",'DoorDash-Import'!1:1,0)),INDEX('DoorDash-Import'!A:Z,0,MATCH("Store Name",'DoorDash-Import'!1:1,0)),"Moto Medi 3rd"),0) | C6: 0 | D6: =B6-C6 | E6: =IF(C6>0,(B6-C6)/C6,0)
A7: UberEats Net Revenue | B7: =IFERROR(SUMIFS(INDEX('UberEats-Import'!A:Z,0,MATCH("Net Payout",'UberEats-Import'!1:1,0)),INDEX('UberEats-Import'!A:Z,0,MATCH("Restaurant Name",'UberEats-Import'!1:1,0)),"Moto Medi 3rd"),0) | C7: 0 | D7: =B7-C7 | E7: =IF(C7>0,(B7-C7)/C7,0)
A8: Grubhub Net Revenue | B8: =IFERROR(SUMIFS(INDEX('Grubhub-Import'!A:Z,0,MATCH("Net Payout",'Grubhub-Import'!1:1,0)),INDEX('Grubhub-Import'!A:Z,0,MATCH("Restaurant",'Grubhub-Import'!1:1,0)),"Moto Medi 3rd"),0) | C8: 0 | D8: =B8-C8 | E8: =IF(C8>0,(B8-C8)/C8,0)
A9: Total Net Revenue | B9: =SUM(B5:B8) | C9: =IFERROR(INDEX('Prior-Week'!A:Z,MATCH(B2-7,'Prior-Week'!A:A,0),12),0) | D9: =B9-C9 | E9: =IF(C9>0,(B9-C9)/C9,0)
A10: Cost Metrics
A12: BEK Purchases | B12: =IFERROR(SUMIF(INDEX('BEK-Import'!A:Z,0,MATCH("Category",'BEK-Import'!1:1,0)),"Food",INDEX('BEK-Import'!A:Z,0,MATCH("Total",'BEK-Import'!1:1,0)))/5,IFERROR(SUMIF(INDEX('BEK-Import'!A:Z,0,MATCH("Total",'BEK-Import'!1:1,0)),">0",INDEX('BEK-Import'!A:Z,0,MATCH("Total",'BEK-Import'!1:1,0)))/5,0))
A13: Purchase Cost % | B13: =IF(B9>0,B12/B9,0) | C13: =IFERROR(INDEX('Prior-Week'!A:Z,MATCH(B2-7,'Prior-Week'!A:A,0),13),0) | D13: =B13-C13 | E13: =IF(C13>0,(B13-C13)/C13,0)
A14: Labor
A16: Est. Labor Cost (manual) | B16: 0
A17: Labor Cost % | B17: =IF(B9>0,B16/B9,0) | C17: =IFERROR(INDEX('Prior-Week'!A:Z,MATCH(B2-7,'Prior-Week'!A:A,0),14),0) | D17: =B17-C17 | E17: =IF(C17>0,(B17-C17)/C17,0)
A18: Volume
A20: Total Orders | B20: =IFERROR(SUMIFS(INDEX('Square-Import'!A:Z,0,MATCH("Order Count",'Square-Import'!1:1,0)),INDEX('Square-Import'!A:Z,0,MATCH("Location",'Square-Import'!1:1,0)),"Moto Medi 3rd"),0)+IFERROR(SUMIFS(INDEX('DoorDash-Import'!A:Z,0,MATCH("Order Count",'DoorDash-Import'!1:1,0)),INDEX('DoorDash-Import'!A:Z,0,MATCH("Store Name",'DoorDash-Import'!1:1,0)),"Moto Medi 3rd"),0)+IFERROR(SUMIFS(INDEX('UberEats-Import'!A:Z,0,MATCH("Trips",'UberEats-Import'!1:1,0)),INDEX('UberEats-Import'!A:Z,0,MATCH("Restaurant Name",'UberEats-Import'!1:1,0)),"Moto Medi 3rd"),0)+IFERROR(SUMIFS(INDEX('Grubhub-Import'!A:Z,0,MATCH("Orders",'Grubhub-Import'!1:1,0)),INDEX('Grubhub-Import'!A:Z,0,MATCH("Restaurant",'Grubhub-Import'!1:1,0)),"Moto Medi 3rd"),0) | C20: =IFERROR(INDEX('Prior-Week'!A:Z,MATCH(B2-7,'Prior-Week'!A:A,0),15),0) | D20: =B20-C20 | E20: =IF(C20>0,(B20-C20)/C20,0)
A21: Avg Ticket Size | B21: =IF(B20>0,B9/B20,0) | C21: =IFERROR(INDEX('Prior-Week'!A:Z,MATCH(B2-7,'Prior-Week'!A:A,0),16),0) | D21: =B21-C21 | E21: =IF(C21>0,(B21-C21)/C21,0)
A23: [MM3] Labor Cost requires manual entry — enter weekly labor total in the yellow B16 cell. Phase 2 automates via Square Labor CSV import (PAY-01).

Sheet TS1-Calc
A1: Tikka Shack 1
A2: Week Ending: | B2: ='Summary'!B2
B3: This Week | C3: Prior Week | D3: WoW Change | E3: WoW %
A4: Revenue Breakdown
A5: Square Net Sales | B5: =IFERROR(SUMIFS(INDEX('Square-Import'!A:Z,0,MATCH("Net Sales",'Square-Import'!1:1,0)),INDEX('Square-Import'!A:Z,0,MATCH("Location",'Square-Import'!1:1,0)),"Tikka Shack 1"),0) | C5: 0 | D5: =B5-C5 | E5: =IF(C5>0,(B5-C5)/C5,0)
A6: DoorDash Net Revenue | B6: =IFERROR(SUMIFS(INDEX('DoorDash-Import'!A:Z,0,MATCH("Net Payout",'DoorDash-Import'!1:1,0)),INDEX('DoorDash-Import'!A:Z,0,MATCH("Store Name",'DoorDash-Import'!1:1,0)),"Tikka Shack 1"),0) | C6: 0 | D6: =B6-C6 | E6: =IF(C6>0,(B6-C6)/C6,0)
A7: UberEats Net Revenue | B7: =IFERROR(SUMIFS(INDEX('UberEats-Import'!A:Z,0,MATCH("Net Payout",'UberEats-Import'!1:1,0)),INDEX('UberEats-Import'!A:Z,0,MATCH("Restaurant Name",'UberEats-Import'!1:1,0)),"Tikka Shack 1"),0) | C7: 0 | D7: =B7-C7 | E7: =IF(C7>0,(B7-C7)/C7,0)
A8: Grubhub Net Revenue | B8: =IFERROR(SUMIFS(INDEX('Grubhub-Import'!A:Z,0,MATCH("Net Payout",'Grubhub-Import'!1:1,0)),INDEX('Grubhub-Import'!A:Z,0,MATCH("Restaurant",'Grubhub-Import'!1:1,0)),"Tikka Shack 1"),0) | C8: 0 | D8: =B8-C8 | E8: =IF(C8>0,(B8-C8)/C8,0)
A9: Total Net Revenue | B9: =SUM(B5:B8) | C9: =IFERROR(INDEX('Prior-Week'!A:Z,MATCH(B2-7,'Prior-Week'!A:A,0),17),0) | D9: =B9-C9 | E9: =IF(C9>0,(B9-C9)/C9,0)
A10: Cost Metrics
A12: BEK Purchases | B12: =IFERROR(SUMIF(INDEX('BEK-Import'!A:Z,0,MATCH("Category",'BEK-Import'!1:1,0)),"Food",INDEX('BEK-Import'!A:Z,0,MATCH("Total",'BEK-Import'!1:1,0)))/5,IFERROR(SUMIF(INDEX('BEK-Import'!A:Z,0,MATCH("Total",'BEK-Import'!1:1,0)),">0",INDEX('BEK-Import'!A:Z,0,MATCH("Total",'BEK-Import'!1:1,0)))/5,0))
A13: Purchase Cost % | B13: =IF(B9>0,B12/B9,0) | C13: =IFERROR(INDEX('Prior-Week'!A:Z,MATCH(B2-7,'Prior-Week'!A:A,0),18),0) | D13: =B13-C13 | E13: =IF(C13>0,(B13-C13)/C13,0)
A14: Labor
A16: Est. Labor Cost (manual) | B16: 0
A17: Labor Cost % | B17: =IF(B9>0,B16/B9,0) | C17: =IFERROR(INDEX('Prior-Week'!A:Z,MATCH(B2-7,'Prior-Week'!A:A,0),19),0) | D17: =B17-C17 | E17: =IF(C17>0,(B17-C17)/C17,0)
A18: Volume
A20: Total Orders | B20: =IFERROR(SUMIFS(INDEX('Square-Import'!A:Z,0,MATCH("Order Count",'Square-Import'!1:1,0)),INDEX('Square-Import'!A:Z,0,MATCH("Location",'Square-Import'!1:1,0)),"Tikka Shack 1"),0)+IFERROR(SUMIFS(INDEX('DoorDash-Import'!A:Z,0,MATCH("Order Count",'DoorDash-Import'!1:1,0)),INDEX('DoorDash-Import'!A:Z,0,MATCH("Store Name",'DoorDash-Import'!1:1,0)),"Tikka Shack 1"),0)+IFERROR(SUMIFS(INDEX('UberEats-Import'!A:Z,0,MATCH("Trips",'UberEats-Import'!1:1,0)),INDEX('UberEats-Import'!A:Z,0,MATCH("Restaurant Name",'UberEats-Import'!1:1,0)),"Tikka Shack 1"),0)+IFERROR(SUMIFS(INDEX('Grubhub-Import'!A:Z,0,MATCH("Orders",'Grubhub-Import'!1:1,0)),INDEX('Grubhub-Import'!A:Z,0,MATCH("Restaurant",'Grubhub-Import'!1:1,0)),"Tikka Shack 1"),0) | C20: =IFERROR(INDEX('Prior-Week'!A:Z,MATCH(B2-7,'Prior-Week'!A:A,0),20),0) | D20: =B20-C20 | E20: =IF(C20>0,(B20-C20)/C20,0)
A21: Avg Ticket Size | B21: =IF(B20>0,B9/B20,0) | C21: =IFERROR(INDEX('Prior-Week'!A:Z,MATCH(B2-7,'Prior-Week'!A:A,0),21),0) | D21: =B21-C21 | E21: =IF(C21>0,(B21-C21)/C21,0)
A23: [TS1] Labor Cost requires manual entry — enter weekly labor total in the yellow B16 cell. Phase 2 automates via Square Labor CSV import (PAY-01).

Sheet TS2-Calc
A1: Tikka Shack 2
A2: Week Ending: | B2: ='Summary'!B2
B3: This Week | C3: Prior Week | D3: WoW Change | E3: WoW %
A4: Revenue Breakdown
A5: Square Net Sales | B5: =IFERROR(SUMIFS(INDEX('Square-Import'!A:Z,0,MATCH("Net Sales",'Square-Import'!1:1,0)),INDEX('Square-Import'!A:Z,0,MATCH("Location",'Square-Import'!1:1,0)),"Tikka Shack 2"),0) | C5: 0 | D5: =B5-C5 | E5: =IF(C5>0,(B5-C5)/C5,0)
A6: DoorDash Net Revenue | B6: =IFERROR(SUMIFS(INDEX('DoorDash-Import'!A:Z,0,MATCH("Net Payout",'DoorDash-Import'!1:1,0)),INDEX('DoorDash-Import'!A:Z,0,MATCH("Store Name",'DoorDash-Import'!1:1,0)),"Tikka Shack 2"),0) | C6: 0 | D6: =B6-C6 | E6: =IF(C6>0,(B6-C6)/C6,0)
A7: UberEats Net Revenue | B7: =IFERROR(SUMIFS(INDEX('UberEats-Import'!A:Z,0,MATCH("Net Payout",'UberEats-Import'!1:1,0)),INDEX('UberEats-Import'!A:Z,0,MATCH("Restaurant Name",'UberEats-Import'!1:1,0)),"Tikka Shack 2"),0) | C7: 0 | D7: =B7-C7 | E7: =IF(C7>0,(B7-C7)/C7,0)
A8: Grubhub Net Revenue | B8: =IFERROR(SUMIFS(INDEX('Grubhub-Import'!A:Z,0,MATCH("Net Payout",'Grubhub-Import'!1:1,0)),INDEX('Grubhub-Import'!A:Z,0,MATCH("Restaurant",'Grubhub-Import'!1:1,0)),"Tikka Shack 2"),0) | C8: 0 | D8: =B8-C8 | E8: =IF(C8>0,(B8-C8)/C8,0)
A9: Total Net Revenue | B9: =SUM(B5:B8) | C9: =IFERROR(INDEX('Prior-Week'!A:Z,MATCH(B2-7,'Prior-Week'!A:A,0),22),0) | D9: =B9-C9 | E9: =IF(C9>0,(B9-C9)/C9,0)
A10: Cost Metrics
A12: BEK Purchases | B12: =IFERROR(SUMIF(INDEX('BEK-Import'!A:Z,0,MATCH("Category",'BEK-Import'!1:1,0)),"Food",INDEX('BEK-Import'!A:Z,0,MATCH("Total",'BEK-Import'!1:1,0)))/5,IFERROR(SUMIF(INDEX('BEK-Import'!A:Z,0,MATCH("Total",'BEK-Import'!1:1,0)),">0",INDEX('BEK-Import'!A:Z,0,MATCH("Total",'BEK-Import'!1:1,0)))/5,0))
A13: Purchase Cost % | B13: =IF(B9>0,B12/B9,0) | C13: =IFERROR(INDEX('Prior-Week'!A:Z,MATCH(B2-7,'Prior-Week'!A:A,0),23),0) | D13: =B13-C13 | E13: =IF(C13>0,(B13-C13)/C13,0)
A14: Labor
A16: Est. Labor Cost (manual) | B16: 0
A17: Labor Cost % | B17: =IF(B9>0,B16/B9,0) | C17: =IFERROR(INDEX('Prior-Week'!A:Z,MATCH(B2-7,'Prior-Week'!A:A,0),24),0) | D17: =B17-C17 | E17: =IF(C17>0,(B17-C17)/C17,0)
A18: Volume
A20: Total Orders | B20: =IFERROR(SUMIFS(INDEX('Square-Import'!A:Z,0,MATCH("Order Count",'Square-Import'!1:1,0)),INDEX('Square-Import'!A:Z,0,MATCH("Location",'Square-Import'!1:1,0)),"Tikka Shack 2"),0)+IFERROR(SUMIFS(INDEX('DoorDash-Import'!A:Z,0,MATCH("Order Count",'DoorDash-Import'!1:1,0)),INDEX('DoorDash-Import'!A:Z,0,MATCH("Store Name",'DoorDash-Import'!1:1,0)),"Tikka Shack 2"),0)+IFERROR(SUMIFS(INDEX('UberEats-Import'!A:Z,0,MATCH("Trips",'UberEats-Import'!1:1,0)),INDEX('UberEats-Import'!A:Z,0,MATCH("Restaurant Name",'UberEats-Import'!1:1,0)),"Tikka Shack 2"),0)+IFERROR(SUMIFS(INDEX('Grubhub-Import'!A:Z,0,MATCH("Orders",'Grubhub-Import'!1:1,0)),INDEX('Grubhub-Import'!A:Z,0,MATCH("Restaurant",'Grubhub-Import'!1:1,0)),"Tikka Shack 2"),0) | C20: =IFERROR(INDEX('Prior-Week'!A:Z,MATCH(B2-7,'Prior-Week'!A:A,0),25),0) | D20: =B20-C20 | E20: =IF(C20>0,(B20-C20)/C20,0)
A21: Avg Ticket Size | B21: =IF(B20>0,B9/B20,0) | C21: =IFERROR(INDEX('Prior-Week'!A:Z,MATCH(B2-7,'Prior-Week'!A:A,0),26),0) | D21: =B21-C21 | E21: =IF(C21>0,(B21-C21)/C21,0)
A23: [TS2] Labor Cost requires manual entry — enter weekly labor total in the yellow B16 cell. Phase 2 automates via Square Labor CSV import (PAY-01).

Sheet Summary
A1: Weekly Report Summary
A2: Week Ending:
B4: Moto Medi Lubbock | C4: Moto Medi Amarillo | D4: Moto Medi 3rd | E4: Tikka Shack 1 | F4: Tikka Shack 2
A5: Net Revenue | B5: ='MML-Calc'!B9 | C5: ='MMA-Calc'!B9 | D5: ='MM3-Calc'!B9 | E5: ='TS1-Calc'!B9 | F5: ='TS2-Calc'!B9
A6: WoW | B6: ='MML-Calc'!E9 | C6: ='MMA-Calc'!E9 | D6: ='MM3-Calc'!E9 | E6: ='TS1-Calc'!E9 | F6: ='TS2-Calc'!E9
A7: Purchase Cost % | B7: ='MML-Calc'!B13 | C7: ='MMA-Calc'!B13 | D7: ='MM3-Calc'!B13 | E7: ='TS1-Calc'!B13 | F7: ='TS2-Calc'!B13
A8: WoW | B8: ='MML-Calc'!E13 | C8: ='MMA-Calc'!E13 | D8: ='MM3-Calc'!E13 | E8: ='TS1-Calc'!E13 | F8: ='TS2-Calc'!E13
A9: Labor Cost % | B9: ='MML-Calc'!B17 | C9: ='MMA-Calc'!B17 | D9: ='MM3-Calc'!B17 | E9: ='TS1-Calc'!B17 | F9: ='TS2-Calc'!B17
A10: WoW | B10: ='MML-Calc'!E17 | C10: ='MMA-Calc'!E17 | D10: ='MM3-Calc'!E17 | E10: ='TS1-Calc'!E17 | F10: ='TS2-Calc'!E17
A11: Order Volume | B11: ='MML-Calc'!B20 | C11: ='MMA-Calc'!B20 | D11: ='MM3-Calc'!B20 | E11: ='TS1-Calc'!B20 | F11: ='TS2-Calc'!B20
A12: WoW | B12: ='MML-Calc'!E20 | C12: ='MMA-Calc'!E20 | D12: ='MM3-Calc'!E20 | E12: ='TS1-Calc'!E20 | F12: ='TS2-Calc'!E20
A13: Avg Ticket | B13: ='MML-Calc'!B21 | C13: ='MMA-Calc'!B21 | D13: ='MM3-Calc'!B21 | E13: ='TS1-Calc'!B21 | F13: ='TS2-Calc'!B21
A14: WoW | B14: ='MML-Calc'!E21 | C14: ='MMA-Calc'!E21 | D14: ='MM3-Calc'!E21 | E14: ='TS1-Calc'!E21 | F14: ='TS2-Calc'!E21
A17: Notes
A18: Purchase Cost % = BEK food purchases (company-wide, divided by 5 locations) / net revenue. Not true COGS — does not include inventory variance or waste.
A19: Labor Cost % is estimated from manual entry in each Location Calc tab. Phase 2 automates this via Square Labor CSV import.
A20: All delivery revenue (DoorDash, UberEats, Grubhub) uses net payout after platform fees/commissions.

Sheet Labor-Import
A1: PLACEHOLDER HEADERS — Update row 2 to match your actual Square Labor CSV export column names exactly.
A2: Date | B2: Employee Name | C2: Location | D2: Clock In | E2: Clock Out | F2: Regular Hours | G2: Overtime Hours | H2: Total Hours
A3: [Date — text/date] | B3: =IF(ISTEXT(INDEX(Labor-Import!A:Z,4,MATCH("Employee Name",Labor-Import!2:2,0))),"OK","CHECK - Employee Name should be text") | C3: =IF(ISTEXT(INDEX(Labor-Import!A:Z,4,MATCH("Location",Labor-Import!2:2,0))),"OK","CHECK - Location should be text") | D3: [Clock In — text/date] | E3: [Clock Out — text/date] | F3: =IF(ISNUMBER(INDEX(Labor-Import!A:Z,4,MATCH("Regular Hours",Labor-Import!2:2,0))),"OK","PASTE ERROR - Regular Hours is not a number") | G3: =IF(ISNUMBER(INDEX(Labor-Import!A:Z,4,MATCH("Overtime Hours",Labor-Import!2:2,0))),"OK","PASTE ERROR - Overtime Hours is not a number") | H3: =IF(ISNUMBER(INDEX(Labor-Import!A:Z,4,MATCH("Total Hours",Labor-Import!2:2,0))),"OK","PASTE ERROR - Total Hours is not a number")
A4: 2026-03-09 | B4: Marcus Johnson | C4: Moto Medi Lubbock | D4: 08:00 | E4: 16:00 | F4: 8 | G4: 0 | H4: 8
A5: 2026-03-09 | B5: Ashley Torres | C5: Moto Medi Lubbock | D5: 10:00 | E5: 18:00 | F5: 8 | G5: 0 | H5: 8
A6: 2026-03-09 | B6: Devon Scott | C6: Moto Medi Lubbock | D6: 14:00 | E6: 18:00 | F6: 4 | G6: 0 | H6: 4
A7: 2026-03-09 | B7: Robert Kim | C7: Moto Medi Amarillo | D7: 09:00 | E7: 17:00 | F7: 8 | G7: 0 | H7: 8
A8: 2026-03-09 | B8: Destiny Williams | C8: Moto Medi Amarillo | D8: 11:00 | E8: 19:00 | F8: 8 | G8: 0 | H8: 8
A9: 2026-03-09 | B9: Jake Hernandez | C9: Moto Medi 3rd | D9: 08:00 | E9: 16:00 | F9: 8 | G9: 0 | H9: 8
A10: 2026-03-09 | B10: Priya Patel | C10: Tikka Shack 1 | D10: 09:00 | E10: 17:00 | F10: 8 | G10: 0 | H10: 8
A11: 2026-03-09 | B11: Carlos Rivera | C11: Tikka Shack 1 | D11: 12:00 | E11: 20:00 | F11: 8 | G11: 0 | H11: 8
A12: 2026-03-09 | B12: Keisha Brown | C12: Tikka Shack 2 | D12: 10:00 | E12: 18:00 | F12: 8 | G12: 0 | H12: 8
A13: 2026-03-09 | B13: Jasmine Lee | C13: Tikka Shack 2 | D13: 14:00 | E13: 18:00 | F13: 4 | G13: 0 | H13: 4
A14: 2026-03-10 | B14: Marcus Johnson | C14: Moto Medi Lubbock | D14: 08:00 | E14: 16:00 | F14: 8 | G14: 0 | H14: 8
A15: 2026-03-10 | B15: Marcus Johnson | C15: Moto Medi Amarillo | D15: 17:00 | E15: 20:00 | F15: 3 | G15: 0 | H15: 3
... A51: 2026-03-13 | B51: Jasmine Lee | C51: Tikka Shack 2 | D51: 14:00 | E51: 18:00 | F51: 4 | G51: 0 | H51: 4
A53: Last Updated:

Sheet Overtime-Tracker
A1: Week Starting: | B1: 2026-03-09
A3: Employee Name | B3: Mon | C3: Tue | D3: Wed | E3: Thu | F3: Fri | G3: Sat | H3: Sun | I3: Weekly Total | J3: Overtime Hrs | K3: Regular Hrs | L3: Status
A4: Marcus Johnson | B4: =SUMIFS(INDEX('Labor-Import'!A:Z,0,MATCH("Total Hours",'Labor-Import'!2:2,0)),INDEX('Labor-Import'!A:Z,0,MATCH("Employee Name",'Labor-Import'!2:2,0)),A4,INDEX('Labor-Import'!A:Z,0,MATCH("Date",'Labor-Import'!2:2,0)),B$1+0) | C4: =SUMIFS(INDEX('Labor-Import'!A:Z,0,MATCH("Total Hours",'Labor-Import'!2:2,0)),INDEX('Labor-Import'!A:Z,0,MATCH("Employee Name",'Labor-Import'!2:2,0)),A4,INDEX('Labor-Import'!A:Z,0,MATCH("Date",'Labor-Import'!2:2,0)),B$1+1) | D4: =SUMIFS(INDEX('Labor-Import'!A:Z,0,MATCH("Total Hours",'Labor-Import'!2:2,0)),INDEX('Labor-Import'!A:Z,0,MATCH("Employee Name",'Labor-Import'!2:2,0)),A4,INDEX('Labor-Import'!A:Z,0,MATCH("Date",'Labor-Import'!2:2,0)),B$1+2) | E4: =SUMIFS(INDEX('Labor-Import'!A:Z,0,MATCH("Total Hours",'Labor-Import'!2:2,0)),INDEX('Labor-Import'!A:Z,0,MATCH("Employee Name",'Labor-Import'!2:2,0)),A4,INDEX('Labor-Import'!A:Z,0,MATCH("Date",'Labor-Import'!2:2,0)),B$1+3) | F4: =SUMIFS(INDEX('Labor-Import'!A:Z,0,MATCH("Total Hours",'Labor-Import'!2:2,0)),INDEX('Labor-Import'!A:Z,0,MATCH("Employee Name",'Labor-Import'!2:2,0)),A4,INDEX('Labor-Import'!A:Z,0,MATCH("Date",'Labor-Import'!2:2,0)),B$1+4) | G4: =SUMIFS(INDEX('Labor-Import'!A:Z,0,MATCH("Total Hours",'Labor-Import'!2:2,0)),INDEX('Labor-Import'!A:Z,0,MATCH("Employee Name",'Labor-Import'!2:2,0)),A4,INDEX('Labor-Import'!A:Z,0,MATCH("Date",'Labor-Import'!2:2,0)),B$1+5) | H4: =SUMIFS(INDEX('Labor-Import'!A:Z,0,MATCH("Total Hours",'Labor-Import'!2:2,0)),INDEX('Labor-Import'!A:Z,0,MATCH("Employee Name",'Labor-Import'!2:2,0)),A4,INDEX('Labor-Import'!A:Z,0,MATCH("Date",'Labor-Import'!2:2,0)),B$1+6) | I4: =SUM(B4:H4) | J4: =MAX(I4-40,0) | K4: =MIN(I4,40) | L4: =IF(I4>=38,"HIGH",IF(I4>=32,"WARN","OK"))
A5: Ashley Torres | B5: =SUMIFS(INDEX('Labor-Import'!A:Z,0,MATCH("Total Hours",'Labor-Import'!2:2,0)),INDEX('Labor-Import'!A:Z,0,MATCH("Employee Name",'Labor-Import'!2:2,0)),A5,INDEX('Labor-Import'!A:Z,0,MATCH("Date",'Labor-Import'!2:2,0)),B$1+0) | C5: =SUMIFS(INDEX('Labor-Import'!A:Z,0,MATCH("Total Hours",'Labor-Import'!2:2,0)),INDEX('Labor-Import'!A:Z,0,MATCH("Employee Name",'Labor-Import'!2:2,0)),A5,INDEX('Labor-Import'!A:Z,0,MATCH("Date",'Labor-Import'!2:2,0)),B$1+1) | D5: =SUMIFS(INDEX('Labor-Import'!A:Z,0,MATCH("Total Hours",'Labor-Import'!2:2,0)),INDEX('Labor-Import'!A:Z,0,MATCH("Employee Name",'Labor-Import'!2:2,0)),A5,INDEX('Labor-Import'!A:Z,0,MATCH("Date",'Labor-Import'!2:2,0)),B$1+2) | E5: =SUMIFS(INDEX('Labor-Import'!A:Z,0,MATCH("Total Hours",'Labor-Import'!2:2,0)),INDEX('Labor-Import'!A:Z,0,MATCH("Employee Name",'Labor-Import'!2:2,0)),A5,INDEX('Labor-Import'!A:Z,0,MATCH("Date",'Labor-Import'!2:2,0)),B$1+3) | F5: =SUMIFS(INDEX('Labor-Import'!A:Z,0,MATCH("Total Hours",'Labor-Import'!2:2,0)),INDEX('Labor-Import'!A:Z,0,MATCH("Employee Name",'Labor-Import'!2:2,0)),A5,INDEX('Labor-Import'!A:Z,0,MATCH("Date",'Labor-Import'!2:2,0)),B$1+4) | G5: =SUMIFS(INDEX('Labor-Import'!A:Z,0,MATCH("Total Hours",'Labor-Import'!2:2,0)),INDEX('Labor-Import'!A:Z,0,MATCH("Employee Name",'Labor-Import'!2:2,0)),A5,INDEX('Labor-Import'!A:Z,0,MATCH("Date",'Labor-Import'!2:2,0)),B$1+5) | H5: =SUMIFS(INDEX('Labor-Import'!A:Z,0,MATCH("Total Hours",'Labor-Import'!2:2,0)),INDEX('Labor-Import'!A:Z,0,MATCH("Employee Name",'Labor-Import'!2:2,0)),A5,INDEX('Labor-Import'!A:Z,0,MATCH("Date",'Labor-Import'!2:2,0)),B$1+6) | I5: =SUM(B5:H5) | J5: =MAX(I5-40,0) | K5: =MIN(I5,40) | L5: =IF(I5>=38,"HIGH",IF(I5>=32,"WARN","OK"))
A6: Devon Scott | B6: =SUMIFS(INDEX('Labor-Import'!A:Z,0,MATCH("Total Hours",'Labor-Import'!2:2,0)),INDEX('Labor-Import'!A:Z,0,MATCH("Employee Name",'Labor-Import'!2:2,0)),A6,INDEX('Labor-Import'!A:Z,0,MATCH("Date",'Labor-Import'!2:2,0)),B$1+0) | C6: =SUMIFS(INDEX('Labor-Import'!A:Z,0,MATCH("Total Hours",'Labor-Import'!2:2,0)),INDEX('Labor-Import'!A:Z,0,MATCH("Employee Name",'Labor-Import'!2:2,0)),A6,INDEX('Labor-Import'!A:Z,0,MATCH("Date",'Labor-Import'!2:2,0)),B$1+1) | D6: =SUMIFS(INDEX('Labor-Import'!A:Z,0,MATCH("Total Hours",'Labor-Import'!2:2,0)),INDEX('Labor-Import'!A:Z,0,MATCH("Employee Name",'Labor-Import'!2:2,0)),A6,INDEX('Labor-Import'!A:Z,0,MATCH("Date",'Labor-Import'!2:2,0)),B$1+2) | E6: =SUMIFS(INDEX('Labor-Import'!A:Z,0,MATCH("Total Hours",'Labor-Import'!2:2,0)),INDEX('Labor-Import'!A:Z,0,MATCH("Employee Name",'Labor-Import'!2:2,0)),A6,INDEX('Labor-Import'!A:Z,0,MATCH("Date",'Labor-Import'!2:2,0)),B$1+3) | F6: =SUMIFS(INDEX('Labor-Import'!A:Z,0,MATCH("Total Hours",'Labor-Import'!2:2,0)),INDEX('Labor-Import'!A:Z,0,MATCH("Employee Name",'Labor-Import'!2:2,0)),A6,INDEX('Labor-Import'!A:Z,0,MATCH("Date",'Labor-Import'!2:2,0)),B$1+4) | G6: =SUMIFS(INDEX('Labor-Import'!A:Z,0,MATCH("Total Hours",'Labor-Import'!2:2,0)),INDEX('Labor-Import'!A:Z,0,MATCH("Employee Name",'Labor-Import'!2:2,0)),A6,INDEX('Labor-Import'!A:Z,0,MATCH("Date",'Labor-Import'!2:2,0)),B$1+5) | H6: =SUMIFS(INDEX('Labor-Import'!A:Z,0,MATCH("Total Hours",'Labor-Import'!2:2,0)),INDEX('Labor-Import'!A:Z,0,MATCH("Employee Name",'Labor-Import'!2:2,0)),A6,INDEX('Labor-Import'!A:Z,0,MATCH("Date",'Labor-Import'!2:2,0)),B$1+6) | I6: =SUM(B6:H6) | J6: =MAX(I6-40,0) | K6: =MIN(I6,40) | L6: =IF(I6>=38,"HIGH",IF(I6>=32,"WARN","OK"))
A7: Robert Kim | B7: =SUMIFS(INDEX('Labor-Import'!A:Z,0,MATCH("Total Hours",'Labor-Import'!2:2,0)),INDEX('Labor-Import'!A:Z,0,MATCH("Employee Name",'Labor-Import'!2:2,0)),A7,INDEX('Labor-Import'!A:Z,0,MATCH("Date",'Labor-Import'!2:2,0)),B$1+0) | C7: =SUMIFS(INDEX('Labor-Import'!A:Z,0,MATCH("Total Hours",'Labor-Import'!2:2,0)),INDEX('Labor-Import'!A:Z,0,MATCH("Employee Name",'Labor-Import'!2:2,0)),A7,INDEX('Labor-Import'!A:Z,0,MATCH("Date",'Labor-Import'!2:2,0)),B$1+1) | D7: =SUMIFS(INDEX('Labor-Import'!A:Z,0,MATCH("Total Hours",'Labor-Import'!2:2,0)),INDEX('Labor-Import'!A:Z,0,MATCH("Employee Name",'Labor-Import'!2:2,0)),A7,INDEX('Labor-Import'!A:Z,0,MATCH("Date",'Labor-Import'!2:2,0)),B$1+2) | E7: =SUMIFS(INDEX('Labor-Import'!A:Z,0,MATCH("Total Hours",'Labor-Import'!2:2,0)),INDEX('Labor-Import'!A:Z,0,MATCH("Employee Name",'Labor-Import'!2:2,0)),A7,INDEX('Labor-Import'!A:Z,0,MATCH("Date",'Labor-Import'!2:2,0)),B$1+3) | F7: =SUMIFS(INDEX('Labor-Import'!A:Z,0,MATCH("Total Hours",'Labor-Import'!2:2,0)),INDEX('Labor-Import'!A:Z,0,MATCH("Employee Name",'Labor-Import'!2:2,0)),A7,INDEX('Labor-Import'!A:Z,0,MATCH("Date",'Labor-Import'!2:2,0)),B$1+4) | G7: =SUMIFS(INDEX('Labor-Import'!A:Z,0,MATCH("Total Hours",'Labor-Import'!2:2,0)),INDEX('Labor-Import'!A:Z,0,MATCH("Employee Name",'Labor-Import'!2:2,0)),A7,INDEX('Labor-Import'!A:Z,0,MATCH("Date",'Labor-Import'!2:2,0)),B$1+5) | H7: =SUMIFS(INDEX('Labor-Import'!A:Z,0,MATCH("Total Hours",'Labor-Import'!2:2,0)),INDEX('Labor-Import'!A:Z,0,MATCH("Employee Name",'Labor-Import'!2:2,0)),A7,INDEX('Labor-Import'!A:Z,0,MATCH("Date",'Labor-Import'!2:2,0)),B$1+6) | I7: =SUM(B7:H7) | J7: =MAX(I7-40,0) | K7: =MIN(I7,40) | L7: =IF(I7>=38,"HIGH",IF(I7>=32,"WARN","OK"))
A8: Destiny Williams | B8: =SUMIFS(INDEX('Labor-Import'!A:Z,0,MATCH("Total Hours",'Labor-Import'!2:2,0)),INDEX('Labor-Import'!A:Z,0,MATCH("Employee Name",'Labor-Import'!2:2,0)),A8,INDEX('Labor-Import'!A:Z,0,MATCH("Date",'Labor-Import'!2:2,0)),B$1+0) | C8: =SUMIFS(INDEX('Labor-Import'!A:Z,0,MATCH("Total Hours",'Labor-Import'!2:2,0)),INDEX('Labor-Import'!A:Z,0,MATCH("Employee Name",'Labor-Import'!2:2,0)),A8,INDEX('Labor-Import'!A:Z,0,MATCH("Date",'Labor-Import'!2:2,0)),B$1+1) | D8: =SUMIFS(INDEX('Labor-Import'!A:Z,0,MATCH("Total Hours",'Labor-Import'!2:2,0)),INDEX('Labor-Import'!A:Z,0,MATCH("Employee Name",'Labor-Import'!2:2,0)),A8,INDEX('Labor-Import'!A:Z,0,MATCH("Date",'Labor-Import'!2:2,0)),B$1+2) | E8: =SUMIFS(INDEX('Labor-Import'!A:Z,0,MATCH("Total Hours",'Labor-Import'!2:2,0)),INDEX('Labor-Import'!A:Z,0,MATCH("Employee Name",'Labor-Import'!2:2,0)),A8,INDEX('Labor-Import'!A:Z,0,MATCH("Date",'Labor-Import'!2:2,0)),B$1+3) | F8: =SUMIFS(INDEX('Labor-Import'!A:Z,0,MATCH("Total Hours",'Labor-Import'!2:2,0)),INDEX('Labor-Import'!A:Z,0,MATCH("Employee Name",'Labor-Import'!2:2,0)),A8,INDEX('Labor-Import'!A:Z,0,MATCH("Date",'Labor-Import'!2:2,0)),B$1+4) | G8: =SUMIFS(INDEX('Labor-Import'!A:Z,0,MATCH("Total Hours",'Labor-Import'!2:2,0)),INDEX('Labor-Import'!A:Z,0,MATCH("Employee Name",'Labor-Import'!2:2,0)),A8,INDEX('Labor-Import'!A:Z,0,MATCH("Date",'Labor-Import'!2:2,0)),B$1+5) | H8: =SUMIFS(INDEX('Labor-Import'!A:Z,0,MATCH("Total Hours",'Labor-Import'!2:2,0)),INDEX('Labor-Import'!A:Z,0,MATCH("Employee Name",'Labor-Import'!2:2,0)),A8,INDEX('Labor-Import'!A:Z,0,MATCH("Date",'Labor-Import'!2:2,0)),B$1+6) | I8: =SUM(B8:H8) | J8: =MAX(I8-40,0) | K8: =MIN(I8,40) | L8: =IF(I8>=38,"HIGH",IF(I8>=32,"WARN","OK"))
A9: Jake Hernandez | B9: =SUMIFS(INDEX('Labor-Import'!A:Z,0,MATCH("Total Hours",'Labor-Import'!2:2,0)),INDEX('Labor-Import'!A:Z,0,MATCH("Employee Name",'Labor-Import'!2:2,0)),A9,INDEX('Labor-Import'!A:Z,0,MATCH("Date",'Labor-Import'!2:2,0)),B$1+0) | C9: =SUMIFS(INDEX('Labor-Import'!A:Z,0,MATCH("Total Hours",'Labor-Import'!2:2,0)),INDEX('Labor-Import'!A:Z,0,MATCH("Employee Name",'Labor-Import'!2:2,0)),A9,INDEX('Labor-Import'!A:Z,0,MATCH("Date",'Labor-Import'!2:2,0)),B$1+1) | D9: =SUMIFS(INDEX('Labor-Import'!A:Z,0,MATCH("Total Hours",'Labor-Import'!2:2,0)),INDEX('Labor-Import'!A:Z,0,MATCH("Employee Name",'Labor-Import'!2:2,0)),A9,INDEX('Labor-Import'!A:Z,0,MATCH("Date",'Labor-Import'!2:2,0)),B$1+2) | E9: =SUMIFS(INDEX('Labor-Import'!A:Z,0,MATCH("Total Hours",'Labor-Import'!2:2,0)),INDEX('Labor-Import'!A:Z,0,MATCH("Employee Name",'Labor-Import'!2:2,0)),A9,INDEX('Labor-Import'!A:Z,0,MATCH("Date",'Labor-Import'!2:2,0)),B$1+3) | F9: =SUMIFS(INDEX('Labor-Import'!A:Z,0,MATCH("Total Hours",'Labor-Import'!2:2,0)),INDEX('Labor-Import'!A:Z,0,MATCH("Employee Name",'Labor-Import'!2:2,0)),A9,INDEX('Labor-Import'!A:Z,0,MATCH("Date",'Labor-Import'!2:2,0)),B$1+4) | G9: =SUMIFS(INDEX('Labor-Import'!A:Z,0,MATCH("Total Hours",'Labor-Import'!2:2,0)),INDEX('Labor-Import'!A:Z,0,MATCH("Employee Name",'Labor-Import'!2:2,0)),A9,INDEX('Labor-Import'!A:Z,0,MATCH("Date",'Labor-Import'!2:2,0)),B$1+5) | H9: =SUMIFS(INDEX('Labor-Import'!A:Z,0,MATCH("Total Hours",'Labor-Import'!2:2,0)),INDEX('Labor-Import'!A:Z,0,MATCH("Employee Name",'Labor-Import'!2:2,0)),A9,INDEX('Labor-Import'!A:Z,0,MATCH("Date",'Labor-Import'!2:2,0)),B$1+6) | I9: =SUM(B9:H9) | J9: =MAX(I9-40,0) | K9: =MIN(I9,40) | L9: =IF(I9>=38,"HIGH",IF(I9>=32,"WARN","OK"))
A10: Priya Patel | B10: =SUMIFS(INDEX('Labor-Import'!A:Z,0,MATCH("Total Hours",'Labor-Import'!2:2,0)),INDEX('Labor-Import'!A:Z,0,MATCH("Employee Name",'Labor-Import'!2:2,0)),A10,INDEX('Labor-Import'!A:Z,0,MATCH("Date",'Labor-Import'!2:2,0)),B$1+0) | C10: =SUMIFS(INDEX('Labor-Import'!A:Z,0,MATCH("Total Hours",'Labor-Import'!2:2,0)),INDEX('Labor-Import'!A:Z,0,MATCH("Employee Name",'Labor-Import'!2:2,0)),A10,INDEX('Labor-Import'!A:Z,0,MATCH("Date",'Labor-Import'!2:2,0)),B$1+1) | D10: =SUMIFS(INDEX('Labor-Import'!A:Z,0,MATCH("Total Hours",'Labor-Import'!2:2,0)),INDEX('Labor-Import'!A:Z,0,MATCH("Employee Name",'Labor-Import'!2:2,0)),A10,INDEX('Labor-Import'!A:Z,0,MATCH("Date",'Labor-Import'!2:2,0)),B$1+2) | E10: =SUMIFS(INDEX('Labor-Import'!A:Z,0,MATCH("Total Hours",'Labor-Import'!2:2,0)),INDEX('Labor-Import'!A:Z,0,MATCH("Employee Name",'Labor-Import'!2:2,0)),A10,INDEX('Labor-Import'!A:Z,0,MATCH("Date",'Labor-Import'!2:2,0)),B$1+3) | F10: =SUMIFS(INDEX('Labor-Import'!A:Z,0,MATCH("Total Hours",'Labor-Import'!2:2,0)),INDEX('Labor-Import'!A:Z,0,MATCH("Employee Name",'Labor-Import'!2:2,0)),A10,INDEX('Labor-Import'!A:Z,0,MATCH("Date",'Labor-Import'!2:2,0)),B$1+4) | G10: =SUMIFS(INDEX('Labor-Import'!A:Z,0,MATCH("Total Hours",'Labor-Import'!2:2,0)),INDEX('Labor-Import'!A:Z,0,MATCH("Employee Name",'Labor-Import'!2:2,0)),A10,INDEX('Labor-Import'!A:Z,0,MATCH("Date",'Labor-Import'!2:2,0)),B$1+5) | H10: =SUMIFS(INDEX('Labor-Import'!A:Z,0,MATCH("Total Hours",'Labor-Import'!2:2,0)),INDEX('Labor-Import'!A:Z,0,MATCH("Employee Name",'Labor-Import'!2:2,0)),A10,INDEX('Labor-Import'!A:Z,0,MATCH("Date",'Labor-Import'!2:2,0)),B$1+6) | I10: =SUM(B10:H10) | J10: =MAX(I10-40,0) | K10: =MIN(I10,40) | L10: =IF(I10>=38,"HIGH",IF(I10>=32,"WARN","OK"))
A11: Carlos Rivera | B11: =SUMIFS(INDEX('Labor-Import'!A:Z,0,MATCH("Total Hours",'Labor-Import'!2:2,0)),INDEX('Labor-Import'!A:Z,0,MATCH("Employee Name",'Labor-Import'!2:2,0)),A11,INDEX('Labor-Import'!A:Z,0,MATCH("Date",'Labor-Import'!2:2,0)),B$1+0) | C11: =SUMIFS(INDEX('Labor-Import'!A:Z,0,MATCH("Total Hours",'Labor-Import'!2:2,0)),INDEX('Labor-Import'!A:Z,0,MATCH("Employee Name",'Labor-Import'!2:2,0)),A11,INDEX('Labor-Import'!A:Z,0,MATCH("Date",'Labor-Import'!2:2,0)),B$1+1) | D11: =SUMIFS(INDEX('Labor-Import'!A:Z,0,MATCH("Total Hours",'Labor-Import'!2:2,0)),INDEX('Labor-Import'!A:Z,0,MATCH("Employee Name",'Labor-Import'!2:2,0)),A11,INDEX('Labor-Import'!A:Z,0,MATCH("Date",'Labor-Import'!2:2,0)),B$1+2) | E11: =SUMIFS(INDEX('Labor-Import'!A:Z,0,MATCH("Total Hours",'Labor-Import'!2:2,0)),INDEX('Labor-Import'!A:Z,0,MATCH("Employee Name",'Labor-Import'!2:2,0)),A11,INDEX('Labor-Import'!A:Z,0,MATCH("Date",'Labor-Import'!2:2,0)),B$1+3) | F11: =SUMIFS(INDEX('Labor-Import'!A:Z,0,MATCH("Total Hours",'Labor-Import'!2:2,0)),INDEX('Labor-Import'!A:Z,0,MATCH("Employee Name",'Labor-Import'!2:2,0)),A11,INDEX('Labor-Import'!A:Z,0,MATCH("Date",'Labor-Import'!2:2,0)),B$1+4) | G11: =SUMIFS(INDEX('Labor-Import'!A:Z,0,MATCH("Total Hours",'Labor-Import'!2:2,0)),INDEX('Labor-Import'!A:Z,0,MATCH("Employee Name",'Labor-Import'!2:2,0)),A11,INDEX('Labor-Import'!A:Z,0,MATCH("Date",'Labor-Import'!2:2,0)),B$1+5) | H11: =SUMIFS(INDEX('Labor-Import'!A:Z,0,MATCH("Total Hours",'Labor-Import'!2:2,0)),INDEX('Labor-Import'!A:Z,0,MATCH("Employee Name",'Labor-Import'!2:2,0)),A11,INDEX('Labor-Import'!A:Z,0,MATCH("Date",'Labor-Import'!2:2,0)),B$1+6) | I11: =SUM(B11:H11) | J11: =MAX(I11-40,0) | K11: =MIN(I11,40) | L11: =IF(I11>=38,"HIGH",IF(I11>=32,"WARN","OK"))
A12: Keisha Brown | B12: =SUMIFS(INDEX('Labor-Import'!A:Z,0,MATCH("Total Hours",'Labor-Import'!2:2,0)),INDEX('Labor-Import'!A:Z,0,MATCH("Employee Name",'Labor-Import'!2:2,0)),A12,INDEX('Labor-Import'!A:Z,0,MATCH("Date",'Labor-Import'!2:2,0)),B$1+0) | C12: =SUMIFS(INDEX('Labor-Import'!A:Z,0,MATCH("Total Hours",'Labor-Import'!2:2,0)),INDEX('Labor-Import'!A:Z,0,MATCH("Employee Name",'Labor-Import'!2:2,0)),A12,INDEX('Labor-Import'!A:Z,0,MATCH("Date",'Labor-Import'!2:2,0)),B$1+1) | D12: =SUMIFS(INDEX('Labor-Import'!A:Z,0,MATCH("Total Hours",'Labor-Import'!2:2,0)),INDEX('Labor-Import'!A:Z,0,MATCH("Employee Name",'Labor-Import'!2:2,0)),A12,INDEX('Labor-Import'!A:Z,0,MATCH("Date",'Labor-Import'!2:2,0)),B$1+2) | E12: =SUMIFS(INDEX('Labor-Import'!A:Z,0,MATCH("Total Hours",'Labor-Import'!2:2,0)),INDEX('Labor-Import'!A:Z,0,MATCH("Employee Name",'Labor-Import'!2:2,0)),A12,INDEX('Labor-Import'!A:Z,0,MATCH("Date",'Labor-Import'!2:2,0)),B$1+3) | F12: =SUMIFS(INDEX('Labor-Import'!A:Z,0,MATCH("Total Hours",'Labor-Import'!2:2,0)),INDEX('Labor-Import'!A:Z,0,MATCH("Employee Name",'Labor-Import'!2:2,0)),A12,INDEX('Labor-Import'!A:Z,0,MATCH("Date",'Labor-Import'!2:2,0)),B$1+4) | G12: =SUMIFS(INDEX('Labor-Import'!A:Z,0,MATCH("Total Hours",'Labor-Import'!2:2,0)),INDEX('Labor-Import'!A:Z,0,MATCH("Employee Name",'Labor-Import'!2:2,0)),A12,INDEX('Labor-Import'!A:Z,0,MATCH("Date",'Labor-Import'!2:2,0)),B$1+5) | H12: =SUMIFS(INDEX('Labor-Import'!A:Z,0,MATCH("Total Hours",'Labor-Import'!2:2,0)),INDEX('Labor-Import'!A:Z,0,MATCH("Employee Name",'Labor-Import'!2:2,0)),A12,INDEX('Labor-Import'!A:Z,0,MATCH("Date",'Labor-Import'!2:2,0)),B$1+6) | I12: =SUM(B12:H12) | J12: =MAX(I12-40,0) | K12: =MIN(I12,40) | L12: =IF(I12>=38,"HIGH",IF(I12>=32,"WARN","OK"))
A13: Jasmine Lee | B13: =SUMIFS(INDEX('Labor-Import'!A:Z,0,MATCH("Total Hours",'Labor-Import'!2:2,0)),INDEX('Labor-Import'!A:Z,0,MATCH("Employee Name",'Labor-Import'!2:2,0)),A13,INDEX('Labor-Import'!A:Z,0,MATCH("Date",'Labor-Import'!2:2,0)),B$1+0) | C13: =SUMIFS(INDEX('Labor-Import'!A:Z,0,MATCH("Total Hours",'Labor-Import'!2:2,0)),INDEX('Labor-Import'!A:Z,0,MATCH("Employee Name",'Labor-Import'!2:2,0)),A13,INDEX('Labor-Import'!A:Z,0,MATCH("Date",'Labor-Import'!2:2,0)),B$1+1) | D13: =SUMIFS(INDEX('Labor-Import'!A:Z,0,MATCH("Total Hours",'Labor-Import'!2:2,0)),INDEX('Labor-Import'!A:Z,0,MATCH("Employee Name",'Labor-Import'!2:2,0)),A13,INDEX('Labor-Import'!A:Z,0,MATCH("Date",'Labor-Import'!2:2,0)),B$1+2) | E13: =SUMIFS(INDEX('Labor-Import'!A:Z,0,MATCH("Total Hours",'Labor-Import'!2:2,0)),INDEX('Labor-Import'!A:Z,0,MATCH("Employee Name",'Labor-Import'!2:2,0)),A13,INDEX('Labor-Import'!A:Z,0,MATCH("Date",'Labor-Import'!2:2,0)),B$1+3) | F13: =SUMIFS(INDEX('Labor-Import'!A:Z,0,MATCH("Total Hours",'Labor-Import'!2:2,0)),INDEX('Labor-Import'!A:Z,0,MATCH("Employee Name",'Labor-Import'!2:2,0)),A13,INDEX('Labor-Import'!A:Z,0,MATCH("Date",'Labor-Import'!2:2,0)),B$1+4) | G13: =SUMIFS(INDEX('Labor-Import'!A:Z,0,MATCH("Total Hours",'Labor-Import'!2:2,0)),INDEX('Labor-Import'!A:Z,0,MATCH("Employee Name",'Labor-Import'!2:2,0)),A13,INDEX('Labor-Import'!A:Z,0,MATCH("Date",'Labor-Import'!2:2,0)),B$1+5) | H13: =SUMIFS(INDEX('Labor-Import'!A:Z,0,MATCH("Total Hours",'Labor-Import'!2:2,0)),INDEX('Labor-Import'!A:Z,0,MATCH("Employee Name",'Labor-Import'!2:2,0)),A13,INDEX('Labor-Import'!A:Z,0,MATCH("Date",'Labor-Import'!2:2,0)),B$1+6) | I13: =SUM(B13:H13) | J13: =MAX(I13-40,0) | K13: =MIN(I13,40) | L13: =IF(I13>=38,"HIGH",IF(I13>=32,"WARN","OK"))

Sheet Payroll-Output
A1: Pay Period Ending: | B1: 2026-03-15
A3: Employee Name | B3: Regular Hours | C3: Overtime Hours | D3: Current Pay Rate | E3: Estimated Gross Pay | F3: Pay Period
A4: ='Overtime-Tracker'!A4 | B4: ='Overtime-Tracker'!K4 | C4: ='Overtime-Tracker'!J4 | D4: =IFERROR(VLOOKUP(A4,'Employee-Roster'!B:D,3,FALSE),"RATE NOT FOUND") | E4: =IFERROR((B4*D4)+(C4*D4*1.5),"") | F4: =$B$1
A5: ='Overtime-Tracker'!A5 | B5: ='Overtime-Tracker'!K5 | C5: ='Overtime-Tracker'!J5 | D5: =IFERROR(VLOOKUP(A5,'Employee-Roster'!B:D,3,FALSE),"RATE NOT FOUND") | E5: =IFERROR((B5*D5)+(C5*D5*1.5),"") | F5: =$B$1
A6: ='Overtime-Tracker'!A6 | B6: ='Overtime-Tracker'!K6 | C6: ='Overtime-Tracker'!J6 | D6: =IFERROR(VLOOKUP(A6,'Employee-Roster'!B:D,3,FALSE),"RATE NOT FOUND") | E6: =IFERROR((B6*D6)+(C6*D6*1.5),"") | F6: =$B$1
A7: ='Overtime-Tracker'!A7 | B7: ='Overtime-Tracker'!K7 | C7: ='Overtime-Tracker'!J7 | D7: =IFERROR(VLOOKUP(A7,'Employee-Roster'!B:D,3,FALSE),"RATE NOT FOUND") | E7: =IFERROR((B7*D7)+(C7*D7*1.5),"") | F7: =$B$1
A8: ='Overtime-Tracker'!A8 | B8: ='Overtime-Tracker'!K8 | C8: ='Overtime-Tracker'!J8 | D8: =IFERROR(VLOOKUP(A8,'Employee-Roster'!B:D,3,FALSE),"RATE NOT FOUND") | E8: =IFERROR((B8*D8)+(C8*D8*1.5),"") | F8: =$B$1
A9: ='Overtime-Tracker'!A9 | B9: ='Overtime-Tracker'!K9 | C9: ='Overtime-Tracker'!J9 | D9: =IFERROR(VLOOKUP(A9,'Employee-Roster'!B:D,3,FALSE),"RATE NOT FOUND") | E9: =IFERROR((B9*D9)+(C9*D9*1.5),"") | F9: =$B$1
A10: ='Overtime-Tracker'!A10 | B10: ='Overtime-Tracker'!K10 | C10: ='Overtime-Tracker'!J10 | D10: =IFERROR(VLOOKUP(A10,'Employee-Roster'!B:D,3,FALSE),"RATE NOT FOUND") | E10: =IFERROR((B10*D10)+(C10*D10*1.5),"") | F10: =$B$1
A11: ='Overtime-Tracker'!A11 | B11: ='Overtime-Tracker'!K11 | C11: ='Overtime-Tracker'!J11 | D11: =IFERROR(VLOOKUP(A11,'Employee-Roster'!B:D,3,FALSE),"RATE NOT FOUND") | E11: =IFERROR((B11*D11)+(C11*D11*1.5),"") | F11: =$B$1
A12: ='Overtime-Tracker'!A12 | B12: ='Overtime-Tracker'!K12 | C12: ='Overtime-Tracker'!J12 | D12: =IFERROR(VLOOKUP(A12,'Employee-Roster'!B:D,3,FALSE),"RATE NOT FOUND") | E12: =IFERROR((B12*D12)+(C12*D12*1.5),"") | F12: =$B$1
A13: ='Overtime-Tracker'!A13 | B13: ='Overtime-Tracker'!K13 | C13: ='Overtime-Tracker'!J13 | D13: =IFERROR(VLOOKUP(A13,'Employee-Roster'!B:D,3,FALSE),"RATE NOT FOUND") | E13: =IFERROR((B13*D13)+(C13*D13*1.5),"") | F13: =$B$1
